<mujoco model="bandage_roll">
  <worldbody>
    <body>
      <body name="object">
        <geom name="bandage_collision" type="box" pos="0 0 0.022"
              size="0.024 0.024 0.022" rgba="0 0 0 0" density="900"
              friction="0.9 0.01 0.001"
              solimp="0.9 0.95 0.001" solref="0.02 1" group="0"/>
        <geom name="bandage_roll_outer" type="cylinder" pos="0 0 0.022"
              size="0.025 0.022" rgba="0.96 0.94 0.88 1"
              contype="0" conaffinity="0" group="1"/>
        <geom name="bandage_roll_middle" type="cylinder" pos="0 0 0.0443"
              size="0.018 0.0008" rgba="0.84 0.80 0.70 1"
              contype="0" conaffinity="0" group="1"/>
        <geom name="bandage_core" type="cylinder" pos="0 0 0.0452"
              size="0.007 0.001" rgba="0.38 0.25 0.14 1"
              contype="0" conaffinity="0" group="1"/>
        <geom name="bandage_tail" type="box" pos="0.038 0 0.004"
              size="0.024 0.016 0.002" rgba="0.96 0.94 0.88 1"
              contype="0" conaffinity="0" group="1"/>
      </body>
      <site name="bottom_site" pos="0 0 0" size="0.003" rgba="0 0 0 0"/>
      <site name="top_site" pos="0 0 0.046" size="0.003" rgba="0 0 0 0"/>
      <site name="horizontal_radius_site" pos="0.062 0 0.022"
            size="0.003" rgba="0 0 0 0"/>
    </body>
  </worldbody>
</mujoco>
